schoology/__init__.py
schoology-2.1.data/scripts/schoology
schoology-2.1.dist-info/LICENSE
schoology-2.1.dist-info/METADATA
schoology-2.1.dist-info/WHEEL
schoology-2.1.dist-info/top_level.txt
schoology-2.1.dist-info/RECORD
